pronunciation_dictionary_utils/__init__.py
pronunciation_dictionary_utils/common.py
pronunciation_dictionary_utils/merging.py
pronunciation_dictionary_utils/pronunciations_map_symbols.py
pronunciation_dictionary_utils/pronunciations_map_symbols_dict.py
pronunciation_dictionary_utils/pronunciations_remove_symbols.py
pronunciation_dictionary_utils/pronunciations_replace_pronunciation.py
pronunciation_dictionary_utils/pronunciations_sorting.py
pronunciation_dictionary_utils/single_pronunciation_selection.py
pronunciation_dictionary_utils/subset_extraction.py
pronunciation_dictionary_utils/validation.py
pronunciation_dictionary_utils/vocabulary_remove_symbols.py
pronunciation_dictionary_utils/weights_normalization.py
pronunciation_dictionary_utils/words_casing_adjustment.py
pronunciation_dictionary_utils/words_remove_symbols.py
pronunciation_dictionary_utils/words_sorting.py
pronunciation_dictionary_utils_cli/__init__.py
pronunciation_dictionary_utils_cli/argparse_helper.py
pronunciation_dictionary_utils_cli/cli.py
pronunciation_dictionary_utils_cli/formatting_adjustment.py
pronunciation_dictionary_utils_cli/globals.py
pronunciation_dictionary_utils_cli/io.py
pronunciation_dictionary_utils_cli/logging_configuration.py
pronunciation_dictionary_utils_cli/merging.py
pronunciation_dictionary_utils_cli/phoneme_set_extraction.py
pronunciation_dictionary_utils_cli/pronunciations_map_symbols.py
pronunciation_dictionary_utils_cli/pronunciations_map_symbols_json.py
pronunciation_dictionary_utils_cli/pronunciations_remove_symbols.py
pronunciation_dictionary_utils_cli/pronunciations_sorting.py
pronunciation_dictionary_utils_cli/single_pronunciation_selection.py
pronunciation_dictionary_utils_cli/subset_extraction.py
pronunciation_dictionary_utils_cli/vocabulary_extraction.py
pronunciation_dictionary_utils_cli/vocabulary_remove_symbols.py
pronunciation_dictionary_utils_cli/weights_normalization.py
pronunciation_dictionary_utils_cli/words_casing_adjustment.py
pronunciation_dictionary_utils-0.0.5.dist-info/LICENSE
pronunciation_dictionary_utils-0.0.5.dist-info/METADATA
pronunciation_dictionary_utils-0.0.5.dist-info/WHEEL
pronunciation_dictionary_utils-0.0.5.dist-info/entry_points.txt
pronunciation_dictionary_utils-0.0.5.dist-info/top_level.txt
pronunciation_dictionary_utils-0.0.5.dist-info/RECORD
