Metadata-Version: 2.1
Name: pronunciation-dictionary-utils
Version: 0.0.5
Summary: CLI and library to modify pronunciation dictionaries (any language).
Author-email: Stefan Taubert <pypi@stefantaubert.com>
Maintainer-email: Stefan Taubert <pypi@stefantaubert.com>
License: MIT
Project-URL: Homepage, https://github.com/stefantaubert/pronunciation-dictionary-utils
Project-URL: Issues, https://github.com/stefantaubert/pronunciation-dictionary-utils/issues
Keywords: ARPAbet,IPA,X-SAMPA,CMU,TTS,Text-to-speech,Speech synthesis,Language,Linguistics
Classifier: Development Status :: 2 - Pre-Alpha
Classifier: Operating System :: OS Independent
Classifier: Operating System :: MacOS
Classifier: Operating System :: POSIX
Classifier: Operating System :: POSIX :: BSD
Classifier: Operating System :: POSIX :: Linux
Classifier: Operating System :: Unix
Classifier: Operating System :: Microsoft :: Windows
Classifier: Programming Language :: Python
Classifier: Programming Language :: Python :: 3
Classifier: Programming Language :: Python :: 3.8
Classifier: Programming Language :: Python :: 3.9
Classifier: Programming Language :: Python :: 3.10
Classifier: Programming Language :: Python :: 3.11
Classifier: Programming Language :: Python :: 3.12
Classifier: License :: OSI Approved :: MIT License
Requires-Python: <3.13,>=3.8
License-File: LICENSE
Requires-Dist: pronunciation-dictionary >=0.0.6
Requires-Dist: ordered-set >=4.1.0
Requires-Dist: tqdm
